setup.py
django_multi_sessions.egg-info/PKG-INFO
django_multi_sessions.egg-info/SOURCES.txt
django_multi_sessions.egg-info/dependency_links.txt
django_multi_sessions.egg-info/not-zip-safe
django_multi_sessions.egg-info/requires.txt
django_multi_sessions.egg-info/top_level.txt
multi_sessions/__init__.py
multi_sessions/session.py
multi_sessions/settings.py
multi_sessions/tests.py
multi_sessions/management/__init__.py
multi_sessions/management/commands/__init__.py
multi_sessions/management/commands/session_migrator_to_redis.py