Metadata-Version: 1.1
Name: django-multi-sessions
Version: 0.1.0
Summary: Multi-sessions backend for Django
Home-page: http://github.com/adw0rd/django-multi-sessions
Author: Mikhail Andreev
Author-email: x11org@gmail.com
License: BSD
Keywords: django,sessions
Platform: UNKNOWN
Classifier: Environment :: Web Environment
Classifier: Programming Language :: Python
Classifier: Framework :: Django
Classifier: License :: OSI Approved :: BSD License
Classifier: Topic :: Software Development :: Libraries :: Application Frameworks
Classifier: Topic :: Software Development :: Libraries :: Python Modules
